{
  "account_total": 106115.48,
  "last_updated": "2026-05-06T15:47:07.178279+00:00",
  "strategies": {
    "MOM": {
      "name": "Momentum",
      "allocated": 15767.68,
      "cash": 339.32,
      "positions": {
        "AMAT": {
          "qty": 4.901702,
          "avg_entry": 397.39047,
          "current": 426.885,
          "market_value": 2092.46,
          "unrealized_pl": 144.57,
          "unrealized_plpc": 0.07422
        },
        "AMD": {
          "qty": 1.24593,
          "avg_entry": 340.853959,
          "current": 415.46,
          "market_value": 517.63,
          "unrealized_pl": 92.95,
          "unrealized_plpc": 0.21888
        },
        "APLD": {
          "qty": 47.846031746,
          "avg_entry": 31.5,
          "current": 41.845,
          "market_value": 2002.117198,
          "unrealized_pl": 494.967198,
          "unrealized_plpc": 0.32841
        },
        "ASML": {
          "qty": 1.03072866,
          "avg_entry": 1462.218,
          "current": 1534.515,
          "market_value": 1581.66859,
          "unrealized_pl": 74.51859,
          "unrealized_plpc": 0.04944
        },
        "GOOGL": {
          "qty": 4.459683,
          "avg_entry": 337.941176,
          "current": 397.11,
          "market_value": 1770.98,
          "unrealized_pl": 263.87,
          "unrealized_plpc": 0.17509
        },
        "INTC": {
          "qty": 15.889876,
          "avg_entry": 97.9282,
          "current": 111.1,
          "market_value": 1765.37,
          "unrealized_pl": 209.3,
          "unrealized_plpc": 0.1345
        },
        "KLAC": {
          "qty": 1.111214,
          "avg_entry": 1802.941166,
          "current": 1800.54,
          "market_value": 2000.79,
          "unrealized_pl": -2.66,
          "unrealized_plpc": -0.00133
        },
        "LRCX": {
          "qty": 7.476495,
          "avg_entry": 260.801322,
          "current": 295.76,
          "market_value": 2211.25,
          "unrealized_pl": 261.37,
          "unrealized_plpc": 0.13404
        },
        "RKLB": {
          "qty": 19.181675,
          "avg_entry": 79.129078,
          "current": 81.4901,
          "market_value": 1563.12,
          "unrealized_pl": 45.29,
          "unrealized_plpc": 0.02984
        },
        "WBD": {
          "qty": 55.166544655,
          "avg_entry": 27.32,
          "current": 27.305,
          "market_value": 1506.322502,
          "unrealized_pl": -0.827498,
          "unrealized_plpc": -0.00055
        }
      },
      "nav_history": [
        {
          "date": "2026-04-14",
          "nav": 15000.0
        },
        {
          "date": "2026-04-15",
          "nav": 5021.06
        },
        {
          "date": "2026-04-16",
          "nav": 15065.6
        },
        {
          "date": "2026-04-17",
          "nav": 15273.86
        },
        {
          "date": "2026-04-20",
          "nav": 15083.68
        },
        {
          "date": "2026-04-21",
          "nav": 15014.48
        },
        {
          "date": "2026-04-22",
          "nav": 15061.32
        },
        {
          "date": "2026-04-23",
          "nav": 15560.49
        },
        {
          "date": "2026-04-24",
          "nav": 16162.62
        },
        {
          "date": "2026-04-27",
          "nav": 15855.65
        },
        {
          "date": "2026-04-28",
          "nav": 15249.14
        },
        {
          "date": "2026-04-29",
          "nav": 15149.92
        },
        {
          "date": "2026-04-30",
          "nav": 15714.29
        },
        {
          "date": "2026-05-01",
          "nav": 15925.21
        },
        {
          "date": "2026-05-04",
          "nav": 15638.84
        },
        {
          "date": "2026-05-06",
          "nav": 17351.03
        }
      ],
      "last_rebalance": "2026-05-04"
    },
    "VAL": {
      "name": "Value Quality",
      "allocated": 10511.79,
      "cash": 2511.08,
      "positions": {
        "ADP": {
          "qty": 9.793514426,
          "avg_entry": 201.37,
          "current": 206.31,
          "market_value": 2020.499961,
          "unrealized_pl": 48.379961,
          "unrealized_plpc": 0.02453
        },
        "AMGN": {
          "qty": 5.810241138,
          "avg_entry": 345.86,
          "current": 330.51,
          "market_value": 1920.342799,
          "unrealized_pl": -89.187201,
          "unrealized_plpc": -0.04438
        },
        "GILD": {
          "qty": 15.130863639,
          "avg_entry": 132.81,
          "current": 134.68,
          "market_value": 2037.824715,
          "unrealized_pl": 28.294715,
          "unrealized_plpc": 0.01408
        },
        "ZTS": {
          "qty": 17.106750659,
          "avg_entry": 117.47,
          "current": 113.955,
          "market_value": 1949.399771,
          "unrealized_pl": -60.130229,
          "unrealized_plpc": -0.02992
        }
      },
      "nav_history": [
        {
          "date": "2026-04-16",
          "nav": 10042.1
        },
        {
          "date": "2026-04-17",
          "nav": 10063.94
        },
        {
          "date": "2026-04-20",
          "nav": 10040.34
        },
        {
          "date": "2026-04-21",
          "nav": 10010.26
        },
        {
          "date": "2026-04-22",
          "nav": 10055.52
        },
        {
          "date": "2026-04-23",
          "nav": 10044.73
        },
        {
          "date": "2026-04-24",
          "nav": 10056.92
        },
        {
          "date": "2026-04-27",
          "nav": 10198.4
        },
        {
          "date": "2026-04-28",
          "nav": 10163.88
        },
        {
          "date": "2026-04-29",
          "nav": 10015.94
        },
        {
          "date": "2026-04-30",
          "nav": 10243.57
        },
        {
          "date": "2026-05-01",
          "nav": 10208.87
        },
        {
          "date": "2026-05-04",
          "nav": 10276.31
        },
        {
          "date": "2026-05-06",
          "nav": 10439.15
        }
      ],
      "last_rebalance": "2026-04-13"
    },
    "QNT": {
      "name": "Quant Factor",
      "allocated": 13139.73,
      "cash": 2574.96,
      "positions": {
        "ADI": {
          "qty": 1.648847345,
          "avg_entry": 380.86,
          "current": 415.3875,
          "market_value": 684.910577,
          "unrealized_pl": 56.930577,
          "unrealized_plpc": 0.09066
        },
        "AMAT": {
          "qty": 2.051434,
          "avg_entry": 397.39047,
          "current": 426.885,
          "market_value": 875.73,
          "unrealized_pl": 60.51,
          "unrealized_plpc": 0.07422
        },
        "AMD": {
          "qty": 1.901664,
          "avg_entry": 340.853959,
          "current": 415.46,
          "market_value": 790.07,
          "unrealized_pl": 141.88,
          "unrealized_plpc": 0.21888
        },
        "C": {
          "qty": 5.18691804,
          "avg_entry": 132.255801,
          "current": 129.115,
          "market_value": 669.708923,
          "unrealized_pl": -16.291077,
          "unrealized_plpc": -0.02375
        },
        "CAT": {
          "qty": 0.784582329,
          "avg_entry": 807.703636,
          "current": 921.0,
          "market_value": 722.600325,
          "unrealized_pl": 88.890325,
          "unrealized_plpc": 0.14027
        },
        "FDX": {
          "qty": 1.809756063,
          "avg_entry": 388.488821,
          "current": 376.0,
          "market_value": 680.46828,
          "unrealized_pl": -22.601719,
          "unrealized_plpc": -0.03215
        },
        "GOOGL": {
          "qty": 1.858369,
          "avg_entry": 337.941176,
          "current": 397.11,
          "market_value": 737.98,
          "unrealized_pl": 109.96,
          "unrealized_plpc": 0.17509
        },
        "HAL": {
          "qty": 15.955113197,
          "avg_entry": 39.451929,
          "current": 40.1761,
          "market_value": 641.014223,
          "unrealized_pl": 11.55423,
          "unrealized_plpc": 0.01836
        },
        "INTC": {
          "qty": 6.612018,
          "avg_entry": 97.9282,
          "current": 111.1,
          "market_value": 734.6,
          "unrealized_pl": 87.1,
          "unrealized_plpc": 0.1345
        },
        "KLAC": {
          "qty": 0.29358,
          "avg_entry": 1802.941166,
          "current": 1800.54,
          "market_value": 528.6,
          "unrealized_pl": -0.71,
          "unrealized_plpc": -0.00133
        },
        "LRCX": {
          "qty": 3.118198,
          "avg_entry": 260.801322,
          "current": 295.76,
          "market_value": 922.24,
          "unrealized_pl": 109.01,
          "unrealized_plpc": 0.13404
        },
        "MPC": {
          "qty": 2.860956719,
          "avg_entry": 219.5,
          "current": 247.77,
          "market_value": 708.859246,
          "unrealized_pl": 80.879246,
          "unrealized_plpc": 0.12879
        },
        "MU": {
          "qty": 0.994071792,
          "avg_entry": 660.908,
          "current": 661.11,
          "market_value": 657.190802,
          "unrealized_pl": 0.200802,
          "unrealized_plpc": 0.00031
        },
        "OXY": {
          "qty": 11.206974716,
          "avg_entry": 57.345538,
          "current": 55.4793,
          "market_value": 621.755112,
          "unrealized_pl": -20.914882,
          "unrealized_plpc": -0.03254
        },
        "PSX": {
          "qty": 3.909968246,
          "avg_entry": 160.61,
          "current": 171.28,
          "market_value": 669.699361,
          "unrealized_pl": 41.719361,
          "unrealized_plpc": 0.06643
        },
        "RKLB": {
          "qty": 0.246202,
          "avg_entry": 79.129078,
          "current": 81.4901,
          "market_value": 20.06,
          "unrealized_pl": 0.58,
          "unrealized_plpc": 0.02984
        },
        "VLO": {
          "qty": 2.689421841,
          "avg_entry": 233.5,
          "current": 236.54,
          "market_value": 636.155842,
          "unrealized_pl": 8.175842,
          "unrealized_plpc": 0.01302
        }
      },
      "nav_history": [
        {
          "date": "2026-04-16",
          "nav": 12552.62
        },
        {
          "date": "2026-04-17",
          "nav": 12557.37
        },
        {
          "date": "2026-04-20",
          "nav": 12554.75
        },
        {
          "date": "2026-04-21",
          "nav": 12511.91
        },
        {
          "date": "2026-04-22",
          "nav": 12546.08
        },
        {
          "date": "2026-04-23",
          "nav": 12815.48
        },
        {
          "date": "2026-04-24",
          "nav": 13120.89
        },
        {
          "date": "2026-04-27",
          "nav": 13144.5
        },
        {
          "date": "2026-04-28",
          "nav": 12895.28
        },
        {
          "date": "2026-04-29",
          "nav": 12926.17
        },
        {
          "date": "2026-04-30",
          "nav": 13263.74
        },
        {
          "date": "2026-05-01",
          "nav": 13407.99
        },
        {
          "date": "2026-05-04",
          "nav": 13398.1
        },
        {
          "date": "2026-05-06",
          "nav": 13876.59
        }
      ],
      "last_rebalance": "2026-05-06"
    },
    "LEV": {
      "name": "Leveraged ETF",
      "allocated": 26279.47,
      "cash": 13726.65,
      "positions": {
        "SPY": {
          "qty": 17.658882448,
          "avg_entry": 710.850193,
          "current": 731.57,
          "market_value": 12918.708632,
          "unrealized_pl": 365.888636,
          "unrealized_plpc": 0.02915
        }
      },
      "nav_history": [
        {
          "date": "2026-04-16",
          "nav": 25105.24
        },
        {
          "date": "2026-04-17",
          "nav": 25105.63
        },
        {
          "date": "2026-04-20",
          "nav": 24625.85
        },
        {
          "date": "2026-04-21",
          "nav": 24722.78
        },
        {
          "date": "2026-04-22",
          "nav": 25284.74
        },
        {
          "date": "2026-04-23",
          "nav": 25654.9
        },
        {
          "date": "2026-04-24",
          "nav": 26068.53
        },
        {
          "date": "2026-04-27",
          "nav": 26448.74
        },
        {
          "date": "2026-04-28",
          "nav": 25862.9
        },
        {
          "date": "2026-04-29",
          "nav": 25899.74
        },
        {
          "date": "2026-04-30",
          "nav": 26293.42
        },
        {
          "date": "2026-05-01",
          "nav": 27345.06
        },
        {
          "date": "2026-05-04",
          "nav": 27333.69
        },
        {
          "date": "2026-05-06",
          "nav": 26645.36
        }
      ],
      "last_rebalance": "2026-05-06"
    },
    "LEV_ST": {
      "name": "Leveraged Short-Term",
      "allocated": 26279.47,
      "cash": 26279.47,
      "positions": {},
      "nav_history": [
        {
          "date": "2026-04-15",
          "nav": 25105.28
        },
        {
          "date": "2026-04-16",
          "nav": 25105.24
        },
        {
          "date": "2026-04-17",
          "nav": 25105.63
        },
        {
          "date": "2026-04-20",
          "nav": 25042.11
        },
        {
          "date": "2026-04-21",
          "nav": 25025.64
        },
        {
          "date": "2026-04-22",
          "nav": 25119.18
        },
        {
          "date": "2026-04-23",
          "nav": 25234.68
        },
        {
          "date": "2026-04-24",
          "nav": 25443.47
        },
        {
          "date": "2026-04-27",
          "nav": 25706.91
        },
        {
          "date": "2026-04-28",
          "nav": 25594.85
        },
        {
          "date": "2026-04-29",
          "nav": 25295.81
        },
        {
          "date": "2026-04-30",
          "nav": 25437.13
        },
        {
          "date": "2026-05-01",
          "nav": 25729.57
        },
        {
          "date": "2026-05-04",
          "nav": 25924.28
        },
        {
          "date": "2026-05-06",
          "nav": 26279.47
        }
      ],
      "last_rebalance": null
    },
    "GRW": {
      "name": "Growth Small Cap",
      "allocated": 13139.73,
      "cash": 13139.73,
      "positions": {},
      "nav_history": [
        {
          "date": "2026-04-15",
          "nav": 0
        },
        {
          "date": "2026-04-16",
          "nav": 12552.62
        },
        {
          "date": "2026-04-17",
          "nav": 12552.82
        },
        {
          "date": "2026-04-20",
          "nav": 12521.05
        },
        {
          "date": "2026-04-21",
          "nav": 12512.82
        },
        {
          "date": "2026-04-22",
          "nav": 12559.59
        },
        {
          "date": "2026-04-23",
          "nav": 12617.34
        },
        {
          "date": "2026-04-24",
          "nav": 12721.73
        },
        {
          "date": "2026-04-27",
          "nav": 12853.45
        },
        {
          "date": "2026-04-28",
          "nav": 12797.42
        },
        {
          "date": "2026-04-29",
          "nav": 12647.9
        },
        {
          "date": "2026-04-30",
          "nav": 12718.57
        },
        {
          "date": "2026-05-01",
          "nav": 12864.79
        },
        {
          "date": "2026-05-04",
          "nav": 12962.14
        },
        {
          "date": "2026-05-06",
          "nav": 13139.73
        }
      ],
      "last_rebalance": null
    }
  },
  "inception": {
    "total": 100000,
    "strategies": {
      "MOM": 25000,
      "VAL": 25000,
      "QNT": 30000,
      "LEV": 20000,
      "LEV_ST": 0,
      "GRW": 0
    },
    "date": "2026-04-10"
  },
  "alerts": [
    {
      "type": "negative_cash",
      "strategy": "MOM",
      "amount": -546.74,
      "ts": "2026-04-10T13:27:54.346116+00:00"
    },
    {
      "type": "negative_cash",
      "strategy": "QNT",
      "amount": -211.27,
      "ts": "2026-04-10T13:27:54.346128+00:00"
    },
    {
      "type": "negative_cash",
      "strategy": "MOM",
      "amount": -785.26,
      "ts": "2026-04-10T13:44:02.381539+00:00"
    },
    {
      "type": "negative_cash",
      "strategy": "QNT",
      "amount": -138.72,
      "ts": "2026-04-10T13:44:02.381553+00:00"
    },
    {
      "type": "negative_cash",
      "strategy": "MOM",
      "amount": -967.18,
      "ts": "2026-04-10T13:56:10.062123+00:00"
    },
    {
      "type": "negative_cash",
      "strategy": "QNT",
      "amount": -124.63,
      "ts": "2026-04-10T13:56:10.062134+00:00"
    },
    {
      "type": "negative_cash",
      "strategy": "MOM",
      "amount": -914.59,
      "ts": "2026-04-10T14:07:06.400087+00:00"
    },
    {
      "type": "negative_cash",
      "strategy": "QNT",
      "amount": -100.72,
      "ts": "2026-04-10T14:07:06.400100+00:00"
    },
    {
      "type": "negative_cash",
      "strategy": "MOM",
      "amount": -851.15,
      "ts": "2026-04-10T14:18:32.263352+00:00"
    },
    {
      "type": "negative_cash",
      "strategy": "QNT",
      "amount": -65.8,
      "ts": "2026-04-10T14:18:32.263373+00:00"
    },
    {
      "type": "negative_cash",
      "strategy": "MOM",
      "amount": -953.0,
      "ts": "2026-04-10T14:34:39.914851+00:00"
    },
    {
      "type": "negative_cash",
      "strategy": "QNT",
      "amount": -36.39,
      "ts": "2026-04-10T14:34:39.914871+00:00"
    },
    {
      "type": "negative_cash",
      "strategy": "MOM",
      "amount": -10000.0,
      "ts": "2026-04-11T16:04:13.482581+00:00"
    },
    {
      "type": "negative_cash",
      "strategy": "VAL",
      "amount": -10000.0,
      "ts": "2026-04-11T16:04:13.482626+00:00"
    },
    {
      "type": "negative_cash",
      "strategy": "QNT",
      "amount": -10000.0,
      "ts": "2026-04-11T16:04:13.482650+00:00"
    },
    {
      "type": "negative_cash",
      "strategy": "MOM",
      "amount": -10000.0,
      "ts": "2026-04-11T16:10:37.910944+00:00"
    },
    {
      "type": "negative_cash",
      "strategy": "VAL",
      "amount": -10000.0,
      "ts": "2026-04-11T16:10:37.910973+00:00"
    },
    {
      "type": "negative_cash",
      "strategy": "QNT",
      "amount": -10000.0,
      "ts": "2026-04-11T16:10:37.910982+00:00"
    },
    {
      "type": "negative_cash",
      "strategy": "MOM",
      "amount": -10000.0,
      "ts": "2026-04-11T16:21:09.333830+00:00"
    },
    {
      "type": "negative_cash",
      "strategy": "VAL",
      "amount": -10000.0,
      "ts": "2026-04-11T16:21:09.333871+00:00"
    },
    {
      "type": "negative_cash",
      "strategy": "QNT",
      "amount": -10000.0,
      "ts": "2026-04-11T16:21:09.333892+00:00"
    },
    {
      "type": "negative_cash",
      "strategy": "MOM",
      "amount": -9580.91,
      "ts": "2026-04-13T15:06:56.564425+00:00"
    },
    {
      "type": "negative_cash",
      "strategy": "VAL",
      "amount": -10000.0,
      "ts": "2026-04-13T15:06:56.564437+00:00"
    },
    {
      "type": "negative_cash",
      "strategy": "LEV",
      "amount": -63.14,
      "ts": "2026-04-20T15:09:28.974460+00:00"
    },
    {
      "type": "negative_cash",
      "strategy": "LEV",
      "amount": -79.61,
      "ts": "2026-04-21T15:03:57.286650+00:00"
    },
    {
      "type": "negative_cash",
      "strategy": "MOM",
      "amount": -299.09,
      "ts": "2026-04-22T15:11:28.012569+00:00"
    },
    {
      "type": "negative_cash",
      "strategy": "MOM",
      "amount": -229.79,
      "ts": "2026-04-23T15:31:07.062900+00:00"
    },
    {
      "type": "negative_cash",
      "strategy": "MOM",
      "amount": -104.52,
      "ts": "2026-04-24T14:58:36.116758+00:00"
    }
  ],
  "account_total_history": [
    {
      "date": "2026-04-09",
      "nav": 99999.99
    },
    {
      "date": "2026-04-10",
      "nav": 100000.0
    },
    {
      "date": "2026-04-11",
      "nav": 99753.34
    },
    {
      "date": "2026-04-13",
      "nav": 100064.03
    },
    {
      "date": "2026-04-14",
      "nav": 99976.73
    },
    {
      "date": "2026-04-15",
      "nav": 100421.11
    },
    {
      "date": "2026-04-16",
      "nav": 100420.97
    },
    {
      "date": "2026-04-17",
      "nav": 100672.93
    },
    {
      "date": "2026-04-20",
      "nav": 100163.44
    },
    {
      "date": "2026-04-21",
      "nav": 100476.72
    },
    {
      "date": "2026-04-22",
      "nav": 100938.72
    },
    {
      "date": "2026-04-23",
      "nav": 101773.86
    },
    {
      "date": "2026-04-24",
      "nav": 102585.25
    },
    {
      "date": "2026-04-27",
      "nav": 102379.38
    },
    {
      "date": "2026-04-28",
      "nav": 101183.23
    },
    {
      "date": "2026-04-29",
      "nav": 101748.52
    },
    {
      "date": "2026-04-30",
      "nav": 102918.29
    },
    {
      "date": "2026-05-01",
      "nav": 103593.83
    },
    {
      "date": "2026-05-04",
      "nav": 103299.47
    },
    {
      "date": "2026-05-05",
      "nav": 105117.87
    },
    {
      "date": "2026-05-06",
      "nav": 106115.48
    }
  ]
}